<drawables xmlns:xsi="http://www.w3.org/2001/XMLSchema-instance" xsi:noNamespaceSchemaLocation="https://developer.garmin.com/downloads/connect-iq/resources.xsd">
    <bitmap id="LauncherIcon" filename="launcher_icon.svg" dithering="none" />

    <bitmap id="BackgroundWhite" filename="background_white.png" dithering="none" />
    <bitmap id="BackgroundGreen" filename="background_green.png" dithering="none" />
    <bitmap id="BackgroundBlue" filename="background_blue.png" dithering="none" />
    <bitmap id="BackgroundRed" filename="background_red.png" dithering="none" />
    <bitmap id="BackgroundPurple" filename="background_purple.png" dithering="none" />
    <bitmap id="BackgroundOrange" filename="background_orange.png" dithering="none" />
    <bitmap id="BackgroundPink" filename="background_pink.png" dithering="none" />

</drawables>
